{
    "QR code登录。":{
        "VN":"Mã QR đăng nhập.",
        "TH":"เข้าสู่ระบบ QR รหัส.",
        "CN":"QR code登录。"
    },
    "登录":{
        "VN":"Đăng nhập",
        "TH":"เข้าสู่ระบบ",
        "CN":"登录"
    },
    "请使用竞博 APP 登录页面或是“我的”页面中的二维码扫描器来扫描二维码。":{
        "VN":"Quét mã QR bằng Trình quét mã của ứng dụng JBO, nằm ở trang hồ sơ.",
        "TH":"สแกน QR ด้วย ระบบแอป JBO ซึ่งตั้งอยู่ที่หน้าข้อมูลส่วนตัว",
        "CN":"请使用竞博 APP 登录页面或是“我的”页面中的二维码扫描器来扫描二维码。"
    },
    "保存":{
        "VN":"Lưu",
        "TH":"บันทึก",
        "CN":"保存"
    },
    "需要用竞博 APP 来进行扫描。还未安装竞博 APP 吗？":{
        "VN":"Cần có ứng dụng JBO để đăng nhập không cần mật khẩu. Bạn chưa có ứng dụng? ",
        "TH":"แอป JBO สำหรับการเข้าสู่ระบบแบบไม่ต้องใช้รหัสผ่าน คุณยังไม่มีแอปใช่ไหม? ",
        "CN":"需要用竞博 APP 来进行扫描。还未安装竞博 APP 吗？"
    },
    "前往下载":{
        "VN":"Tải ngay!",
        "TH":"ดาวน์โหลดตอนนี้!",
        "CN":"前往下载"
    },
    "账号密码登录":{
        "VN":"Đăng nhập thông thường",
        "TH":"การเข้าสู่ระบบปกติ",
        "CN":"账号密码登录"
    },
    "保存成功":{
        "VN":"Lưu Thành Công",
        "TH":"บันทึกสำเร็จ",
        "CN":"保存成功"
    },
    "系统错误":{
        "VN":"Lỗi",
        "TH":"ข้อผิดพลาด",
        "CN":"系统错误"
    },
    "出现错误，请稍后再尝试。":{
        "VN":"Đã xảy ra lỗi. Vui lòng thử lại sau.",
        "TH":"เกิดข้อผิดพลาด โปรดลองอีกครั้งในภายหลัง",
        "CN":"出现错误，请稍后再尝试。"
    },
    "我知道了":{
        "VN":"Đã Hiểu",
        "TH":"เข้าใจแล้ว",
        "CN":"我知道了"
    },
    "刷新":{
        "VN":"Làm Mới",
        "TH":"โหลดใหม่",
        "CN":"刷新"
    },
    "温馨提示：":{
        "VN":"Nhắc:",
        "TH":"แนะนำ:",
        "CN":"温馨提示："
    },
    "确定":{
        "VN":"Đồng ý",
        "TH":"ตกลง",
        "CN":"确定"
    },
    "取消":{
        "VN":"Hủy bỏ",
        "TH":"ยกเลิก",
        "CN":"取消"
    },
    "将为您打开一个新的窗口":{
        "VN":"Một cửa sổ mới sẽ được mở cho trò chơi, hy vọng bạn thích trò chơi này.",
        "TH":"เปิดหน้าต่างใหม่",
        "CN":"将为您打开一个新的窗口"
    },
    "选择语言":{
        "VN":"Chọn ngôn ngữ",
        "TH":"เลือกภาษา",
        "CN":"选择语言"
    }
}